thundera/__init__.py
thundera/thundera.py
thundera/libs/ArchiveHandler.py
thundera/libs/CmdFactory.py
thundera/libs/CtagsHandler.py
thundera/libs/ErrorHandler.py
thundera/libs/ExifHandler.py
thundera/libs/File.py
thundera/libs/FileHandler.py
thundera/libs/FileScanner.py
thundera/libs/FolderScanner.py
thundera/libs/__init__.py
thundera_bsa-0.1.16.dist-info/LICENSE
thundera_bsa-0.1.16.dist-info/METADATA
thundera_bsa-0.1.16.dist-info/NOTICE
thundera_bsa-0.1.16.dist-info/WHEEL
thundera_bsa-0.1.16.dist-info/entry_points.txt
thundera_bsa-0.1.16.dist-info/top_level.txt
thundera_bsa-0.1.16.dist-info/RECORD
