Metadata-Version: 2.1
Name: thundera-bsa
Version: 0.1.16
Summary: Command Line Interface for ThunderaBSA
Home-page: https://github.com/amazon-ospo/thunderabsa-cli
Author: Oscar Valenzuela B.
Author-email: thunderabsa-pypi@amazon.com
License: Apache-2.0
Platform: UNKNOWN
Classifier: Programming Language :: Python :: 3
Classifier: Operating System :: POSIX :: Linux
Classifier: Development Status :: 3 - Alpha
Classifier: License :: OSI Approved :: Apache Software License
Requires-Dist: binaryornot
Requires-Dist: click
Requires-Dist: lief
Requires-Dist: numpy
Requires-Dist: python-magic
Requires-Dist: python-slugify
Requires-Dist: tabulate
Requires-Dist: terminal-banner
